alpha_trader/__init__.py
alpha_trader/achievement/__init__.py
alpha_trader/authentication/__init__.py
alpha_trader/bank_account/__init__.py
alpha_trader/bonds/__init__.py
alpha_trader/cash_transfer_log/__init__.py
alpha_trader/central_bank_reserves/__init__.py
alpha_trader/client/__init__.py
alpha_trader/company/__init__.py
alpha_trader/employment/__init__.py
alpha_trader/filter/__init__.py
alpha_trader/listing/__init__.py
alpha_trader/logging/__init__.py
alpha_trader/miner/__init__.py
alpha_trader/order/__init__.py
alpha_trader/owner/__init__.py
alpha_trader/partner/__init__.py
alpha_trader/poll/__init__.py
alpha_trader/portfolio/__init__.py
alpha_trader/portfolio/position.py
alpha_trader/price/__init__.py
alpha_trader/price/price.py
alpha_trader/price/price_spread.py
alpha_trader/securities_account/__init__.py
alpha_trader/user/__init__.py
alpha_trader/user_profile/__init__.py
alpha_trader/vote/__init__.py
alpha_trader_python-0.6.3.dist-info/METADATA
alpha_trader_python-0.6.3.dist-info/WHEEL
alpha_trader_python-0.6.3.dist-info/RECORD
